rajx/__init__.py
rajx-0.0.4.dist-info/LICENSE.txt
rajx-0.0.4.dist-info/METADATA
rajx-0.0.4.dist-info/WHEEL
rajx-0.0.4.dist-info/top_level.txt
rajx-0.0.4.dist-info/RECORD
