Metadata-Version: 2.1
Name: rajx
Version: 0.0.4
Home-page: https://github.com/MIVI404cyber
Author: MR.MIVI
Author-email: mrrohman092@gmail.com
License: MIT
Classifier: Programming Language :: Python :: 3
Classifier: License :: OSI Approved :: MIT License
Classifier: Operating System :: OS Independent
License-File: LICENSE.txt
